OpenGL/__init__.py
OpenGL/_bytes.py
OpenGL/_configflags.py
OpenGL/_null.py
OpenGL/_opaque.py
OpenGL/acceleratesupport.py
OpenGL/constant.py
OpenGL/constants.py
OpenGL/contextdata.py
OpenGL/converters.py
OpenGL/error.py
OpenGL/extensions.py
OpenGL/images.py
OpenGL/latebind.py
OpenGL/lazywrapper.py
OpenGL/logs.py
OpenGL/plugins.py
OpenGL/version.py
OpenGL/wrapper.py
OpenGL/DLLS/GLE_WIN32_README.txt
OpenGL/DLLS/freeglut32.vc10.dll
OpenGL/DLLS/freeglut32.vc14.dll
OpenGL/DLLS/freeglut32.vc9.dll
OpenGL/DLLS/freeglut64.vc10.dll
OpenGL/DLLS/freeglut64.vc14.dll
OpenGL/DLLS/freeglut64.vc9.dll
OpenGL/DLLS/freeglut_COPYING.txt
OpenGL/DLLS/freeglut_README.txt
OpenGL/DLLS/gle32.vc10.dll
OpenGL/DLLS/gle32.vc14.dll
OpenGL/DLLS/gle32.vc9.dll
OpenGL/DLLS/gle64.vc10.dll
OpenGL/DLLS/gle64.vc14.dll
OpenGL/DLLS/gle64.vc9.dll
OpenGL/DLLS/gle_AUTHORS
OpenGL/DLLS/gle_COPYING
OpenGL/DLLS/gle_COPYING.src
PyOpenGL-3.1.9a1.dist-info/METADATA
PyOpenGL-3.1.9a1.dist-info/WHEEL
PyOpenGL-3.1.9a1.dist-info/top_level.txt
PyOpenGL-3.1.9a1.dist-info/RECORD
