Metadata-Version: 2.1
Name: PyOpenGL
Version: 3.1.9a1
Summary: Standard OpenGL bindings for Python
Home-page: http://pyopengl.sourceforge.net
Download-URL: https://pypi.org/project/PyOpenGL/
Author: Mike C. Fletcher
Author-email: "Mike C. Fletcher" <mcfletch@vrplumber.com>
Project-URL: Homepage, https://mcfletch.github.io/pyopengl/
Project-URL: Download, https://pypi.org/project/PyOpenGL/
Project-URL: Source, https://github.com/mcfletch/pyopengl
Project-URL: Documentation, https://mcfletch.github.io/pyopengl/documentation/index.html
Keywords: Graphics,3D,OpenGL,GLU,GLUT,GLE,GLX,EXT,ARB,Mesa,ctypes
Classifier: License :: OSI Approved :: BSD License
Classifier: Programming Language :: Python
Classifier: Programming Language :: Python :: 2
Classifier: Programming Language :: Python :: 3
Classifier: Topic :: Multimedia :: Graphics :: 3D Rendering
Classifier: Topic :: Software Development :: Libraries :: Python Modules
Classifier: Intended Audience :: Developers
